funget/__init__.py
funget/config.py
funget/script.py
funget/download/__init__.py
funget/download/common.py
funget/download/core.py
funget/download/multi.py
funget/download/single.py
funget/download/work.py
funget/upload/__init__.py
funget/upload/core.py
funget/upload/single.py
funget-1.0.47.dist-info/METADATA
funget-1.0.47.dist-info/WHEEL
funget-1.0.47.dist-info/entry_points.txt
funget-1.0.47.dist-info/top_level.txt
funget-1.0.47.dist-info/RECORD
