Metadata-Version: 2.4
Name: funget
Version: 1.0.47
Summary: funget
Author-email: 牛哥 <niuliangtao@qq.com>, farfarfun <farfarfun@qq.com>
Maintainer-email: 牛哥 <niuliangtao@qq.com>, farfarfun <farfarfun@qq.com>
Project-URL: Organization, https://github.com/farfarfun
Project-URL: Repository, https://github.com/farfarfun/funget
Project-URL: Releases, https://github.com/farfarfun/funget/releases
Requires-Python: >=3.7
Requires-Dist: funfile>=1.0.15
Requires-Dist: typer-slim>=0.15.2
